LICENSE
pyproject.toml
codelogician/README.md
codelogician/__init__.py
codelogician/tool_cli.py
codelogician/util.py
codelogician/commands/cmd_doc.py
codelogician/commands/cmd_metamodel.py
codelogician/commands/cmd_model.py
codelogician/commands/cmd_search.py
codelogician/commands/cmd_sketches.py
codelogician/commands/cmd_strategy.py
codelogician/commands/utils.py
codelogician/commands/cmd_eval/__init__.py
codelogician/commands/cmd_eval/app.py
codelogician/config/pyiml_config.yaml
codelogician/config/server_config.yaml
codelogician/data/code1/account.py
codelogician/data/code1/asset.py
codelogician/data/code1/bank.py
codelogician/data/code1/currency.py
codelogician/data/code1/ledger.py
codelogician/data/code1/liability.py
codelogician/data/code1/transaction.py
codelogician/data/code2/file1.py
codelogician/data/code2/file2.py
codelogician/data/code2/cldata/iml/file1.iml
codelogician/data/code2/cldata/iml/file2.iml
codelogician/data/code3/file1.py
codelogician/data/code3/file2.py
codelogician/data/code4/.cl_cache
codelogician/data/code4/one.py
codelogician/data/code4/two.py
codelogician/data/code4/cldata/iml/one.iml
codelogician/data/code4/cldata/iml/two.iml
codelogician/data/code5/.cl_cache
codelogician/data/code5/one.py
codelogician/data/code5/three.py
codelogician/data/code5/two.py
codelogician/data/code5/cldata/iml/one.iml
codelogician/data/code5/cldata/iml/three.iml
codelogician/data/code5/cldata/iml/two.iml
codelogician/data/sample_accounting_app/cli.py
codelogician/data/sample_accounting_app/main.py
codelogician/data/sample_accounting_app/models.py
codelogician/data/sample_accounting_app/reports.py
codelogician/data/sample_accounting_app/services.py
codelogician/data/sample_accounting_app/storage.py
codelogician/data/sample_bank_app/account.py
codelogician/data/sample_bank_app/asset.py
codelogician/data/sample_bank_app/bank.py
codelogician/data/sample_bank_app/currency.py
codelogician/data/sample_bank_app/ledger.py
codelogician-2.0.0b8.dist-info/METADATA
codelogician-2.0.0b8.dist-info/WHEEL
codelogician-2.0.0b8.dist-info/entry_points.txt
codelogician-2.0.0b8.dist-info/licenses/LICENSE
codelogician-2.0.0b8.dist-info/RECORD
